.gitignore
resamp_
scratch.py
setup.py
astropy_stark/CCF_interp.py
astropy_stark/CCF_interp_py3.py
astropy_stark/__init__.py
astropy_stark/carolinmake_csv.py
astropy_stark/cff_simple_vortexa.py
astropy_stark/contlags_calc.py
astropy_stark/contlags_plot.py
astropy_stark/cream_lcplot.py
astropy_stark/cream_mergelc.py
astropy_stark/cream_plotlibrary.py
astropy_stark/cream_posterior.py
astropy_stark/cream_trace.py
astropy_stark/fakedat_plotinfo.py
astropy_stark/flux_weighted_rad.py
astropy_stark/get_cream_pars.py
astropy_stark/init.py
astropy_stark/kdestats.py
astropy_stark/kdestats_test.py
astropy_stark/mpfit.py
astropy_stark/my_ccf_vortexa.py
astropy_stark/my_csv2ascii_lc_pandas.py
astropy_stark/my_gplot.py
astropy_stark/my_kateccf.py
astropy_stark/my_kateccf_py3.py
astropy_stark/my_peakestimate.py
astropy_stark/my_psmag_2_sdssmag.py
astropy_stark/myaddnoise.py
astropy_stark/mybnu.py
astropy_stark/mybrokenpowerlaw.py
astropy_stark/mycgs.py
astropy_stark/mychopandsave.py
astropy_stark/mychopandsavemanual.py
astropy_stark/mychopandsavemean.py
astropy_stark/mycomb2to1.py
astropy_stark/myconfidence_ellipse.py
astropy_stark/myconst.py
astropy_stark/myconvolve.py
astropy_stark/mycorner.py
astropy_stark/mycorner_jul6_16.py
astropy_stark/mycrossspec.py
astropy_stark/mycurvefit.py
astropy_stark/mydateconv.py
astropy_stark/mydcf.py
astropy_stark/mydered.py
astropy_stark/mydft.py
astropy_stark/mydiptest.py
astropy_stark/mydiptest_2.py
astropy_stark/mydisksim.py
astropy_stark/mydlflat.py
astropy_stark/mydmag2ratf.py
astropy_stark/myedlum.py
astropy_stark/myerg2mjy.py
astropy_stark/myextmag.py
astropy_stark/myextracttime.py
astropy_stark/myextrapolate.py
astropy_stark/myfake.py
astropy_stark/myfake_amp.py
astropy_stark/myfakelcplot.py
astropy_stark/myfft.py
astropy_stark/myfile_len.py
astropy_stark/myfindnearest.py
astropy_stark/myfitrw.py
astropy_stark/myfitrw_092018.py
astropy_stark/myfitrw_2.py
astropy_stark/myfitrw_current.py
astropy_stark/myfitrw_noiseclean.py
astropy_stark.egg-info/PKG-INFO
astropy_stark.egg-info/SOURCES.txt
astropy_stark.egg-info/dependency_links.txt
astropy_stark.egg-info/not-zip-safe
astropy_stark.egg-info/requires.txt
astropy_stark.egg-info/top_level.txt