Metadata-Version: 1.0
Name: astropy-stark
Version: 1.1.10
Summary: random-custom astronomy functions including making fake accretion disk light curves
Home-page: https://github.com/dstarkey23/pycecream
Author: dstarkey23
Author-email: ds207@st-andrews.ac.uk
License: MIT
Platform: UNKNOWN
